{
  "type": "minecraft:block",
  "pools": [
    {
      "rolls": 1,
      "bonus_rolls": 0,
      "entries": [
        {
          "type": "minecraft:item",
          "name": "minecraft:end_stone",
          "conditions": [
            {
              "condition": "minecraft:match_tool",
              "predicate": {
                "items": "#c:pickaxes_harvest_full_block"
              }
            }
          ]
        }
      ],
      "conditions": [
        {
          "condition": "minecraft:survives_explosion"
        }
      ]
    }
  ]
}
