{
  "type": "minecraft:crafting_shapeless",
  "category": "building",
  "group": "group_te",
  "ingredients": [
    {
      "item": "tough_environment:pile_dirt"
    },
    {
      "item": "tough_environment:pile_dirt"
    },
    {
      "item": "tough_environment:pile_dirt"
    },
    {
      "item": "tough_environment:pile_dirt"
    },
    {
      "item": "tough_environment:pile_dirt"
    },
    {
      "item": "tough_environment:pile_dirt"
    },
    {
      "item": "tough_environment:pile_dirt"
    },
    {
      "item": "tough_environment:pile_dirt"
    }
  ],
  "result": {
    "item": "tough_environment:dirt_loose"
  }
}